hatch_lazyimports/__init__.py
hatch_lazyimports/hooks.py
hatch_lazyimports/lazyimports_hook.py
hatch_lazyimports/py.typed
hatch_lazyimports-0.1.2.dist-info/METADATA
hatch_lazyimports-0.1.2.dist-info/WHEEL
hatch_lazyimports-0.1.2.dist-info/entry_points.txt
hatch_lazyimports-0.1.2.dist-info/RECORD
