Metadata-Version: 2.4
Name: hatch-lazyimports
Version: 0.1.2
Summary: Hatch plugin to automaticilly detect and fill lazyimport entrypoint
Project-URL: Repository, https://github.com/hmiladhia/hatch-lazyimports
Project-URL: Issues, https://github.com/hmiladhia/hatch-lazyimports/issues
Author: Dhia Hmila
License: MIT License
Classifier: Framework :: Hatch
Classifier: Intended Audience :: Developers
Classifier: License :: OSI Approved :: MIT License
Classifier: Programming Language :: Python
Classifier: Programming Language :: Python :: 3
Classifier: Programming Language :: Python :: 3.9
Classifier: Programming Language :: Python :: 3.10
Classifier: Programming Language :: Python :: 3.11
Classifier: Programming Language :: Python :: 3.12
Classifier: Programming Language :: Python :: 3.13
Classifier: Typing :: Typed
Requires-Python: >=3.9
Requires-Dist: auto-lazy-imports>=0.4.2
Requires-Dist: hatchling>=1.0.0
